pysortfolder/__init__.py
pysortfolder/dirsize.py
pysortfolder/tree.py
pysortfolder/version.py
pysortfolder-0.0.4.dist-info/LICENSE
pysortfolder-0.0.4.dist-info/METADATA
pysortfolder-0.0.4.dist-info/WHEEL
pysortfolder-0.0.4.dist-info/top_level.txt
pysortfolder-0.0.4.dist-info/RECORD
