Metadata-Version: 2.1
Name: pysortfolder
Version: 0.0.4
Summary: Sort folders and files by size and display it in folder tree format.
Author-email: Muhammad Yasirroni <48709672+yasirroni@users.noreply.github.com>
Maintainer-email: Muhammad Yasirroni <48709672+yasirroni@users.noreply.github.com>
License: MIT-License
Project-URL: Documentation, https://github.com/yasirroni/pysortfolder#readme
Project-URL: Issues, https://github.com/yasirroni/pysortfolder/issues
Project-URL: Source, https://github.com/yasirroni/pysortfolder
Keywords: sort,folder,size
Classifier: Programming Language :: Python
Classifier: Programming Language :: Python :: 3.7
Classifier: Programming Language :: Python :: 3.8
Classifier: Programming Language :: Python :: 3.9
Classifier: Programming Language :: Python :: 3.10
Classifier: Programming Language :: Python :: 3.11
Classifier: License :: OSI Approved :: MIT License
Classifier: Natural Language :: English
Requires-Python: >=3.7.0
License-File: LICENSE
